{
  "DTW to ATL": {
    "flight 1": {
      "price": "$131",
      "duration": "2h",
      "number of stops": "non stop"
    },
    "flight 2": {
      "price": "$132",
      "duration": "2h",
      "number of stops": "non stop"
    },
    "flight 3": {
      "price": "$178",
      "duration": "2h",
      "number of stops": "non stop"
    },
    "flight 4": {
      "price": "$215",
      "duration": "2h",
      "number of stops": "non stop"
    },
    "flight 5": {
      "price": "$223",
      "duration": "4h",
      "number of stops": "1 stop"
    },
    "flight 6": {
      "price": "$223",
      "duration": "5h",
      "number of stops": "1 stop"
    },
    "flight 7": {
      "price": "$223",
      "duration": "7h",
      "number of stops": "1 stop"
    },
    "flight 8": {
      "price": "$228",
      "duration": "2h",
      "number of stops": "non stop"
    },
    "flight 9": {
      "price": "$241",
      "duration": "4h",
      "number of stops": "1 stop"
    },
    "flight 10": {
      "price": "$379",
      "duration": "9h",
      "number of stops": "2 stops"
    }
  }
}